{"expires":1779357983365,"value":{"code":200,"headers":{"etag":"W/\"IgKDc33iKZ\"","last-modified":"Thu, 14 May 2026 10:06:23 GMT","cache-control":"s-maxage=604800, stale-while-revalidate"},"body":{"prefix":"heroicons","lastModified":1758346379,"aliases":{},"width":24,"height":24,"icons":{"arrow-up-right":{"body":"<path fill=\"none\" stroke=\"currentColor\" stroke-linecap=\"round\" stroke-linejoin=\"round\" stroke-width=\"1.5\" d=\"m4.5 19.5l15-15m0 0H8.25m11.25 0v11.25\"/>"}}}},"mtime":1778753183585,"integrity":"1eNYWk2B0n"}